README.rst
flake8_patch_decorator.py
setup.cfg
setup.py
flake8_patch_decorator_unleashed.egg-info/PKG-INFO
flake8_patch_decorator_unleashed.egg-info/SOURCES.txt
flake8_patch_decorator_unleashed.egg-info/dependency_links.txt
flake8_patch_decorator_unleashed.egg-info/entry_points.txt
flake8_patch_decorator_unleashed.egg-info/not-zip-safe
flake8_patch_decorator_unleashed.egg-info/requires.txt
flake8_patch_decorator_unleashed.egg-info/top_level.txt