Metadata-Version: 1.1
Name: flake8-patch-decorator-unleashed
Version: 1.0.0
Summary: @patch checker plugin for flake8
Home-page: https://github.com/vikingco/flake8-patch-decorator
Author: Unleashed NV
Author-email: technology@unleashed.com
License: MIT
Keywords: flake8 @patch
Platform: UNKNOWN
Classifier: Development Status :: 3 - Alpha
Classifier: Environment :: Console
Classifier: Intended Audience :: Developers
Classifier: License :: OSI Approved :: MIT License
Classifier: Operating System :: OS Independent
Classifier: Programming Language :: Python
Classifier: Programming Language :: Python :: 2
Classifier: Programming Language :: Python :: 3
Classifier: Topic :: Software Development :: Libraries :: Python Modules
Classifier: Topic :: Software Development :: Quality Assurance
